romanticCli/__init__.py
romanticCli/auth.py
romanticCli/backend_service.py
romanticCli/cmd.py
romanticCli/const.py
romanticCli/main.py
romanticCli/services.py
romantic-0.0.5.dist-info/LICENCE
romantic-0.0.5.dist-info/METADATA
romantic-0.0.5.dist-info/WHEEL
romantic-0.0.5.dist-info/entry_points.txt
romantic-0.0.5.dist-info/top_level.txt
romantic-0.0.5.dist-info/RECORD
