Metadata-Version: 2.1
Name: romantic
Version: 0.0.5
Summary: My personalized love-filled CLI tool ❤️
Author-email: Rahul Prajapati <rahul.coder.25@gmail.com>
Project-URL: Homepage, https://github.com/pypa/sampleproject
Project-URL: Issues, https://github.com/pypa/sampleproject/issues
Classifier: Programming Language :: Python :: 3
Classifier: License :: OSI Approved :: MIT License
Classifier: Operating System :: OS Independent
Requires-Python: >=3.8
License-File: LICENCE
Requires-Dist: click
Requires-Dist: requests
Requires-Dist: rich
